{"request":{"pathToCompiledMicroservices":"/Users/abakhtin22/Documents/StaticTools/SARbenchmarks/tms-testbed","organizationPath":"edu/baylor/ecs","outputPath":"/Users/abakhtin22/Documents/StaticTools/SARbenchmarks/tms-testbed-output/rad-raw/rad-graph.json"},"restEntityContexts":[{"resourcePath":"/Users/abakhtin22/Documents/StaticTools/SARbenchmarks/tms-testbed/tms-cms/target/cms-0.0.1-SNAPSHOT.jar","restEntities":[{"url":"http://localhost:10002/exam","applicationName":null,"ribbonServerName":null,"resourcePath":"/Users/abakhtin22/Documents/StaticTools/SARbenchmarks/tms-testbed/tms-cms/target/cms-0.0.1-SNAPSHOT.jar","className":"edu.baylor.ecs.cms.service.EmsService","methodName":"createExam","returnType":"java.lang.Object","path":"/","httpMethod":"POST","pathParams":null,"queryParams":null,"consumeType":null,"produceType":null,"client":true},{"url":"http://localhost:10002/exam","applicationName":null,"ribbonServerName":null,"resourcePath":"/Users/abakhtin22/Documents/StaticTools/SARbenchmarks/tms-testbed/tms-cms/target/cms-0.0.1-SNAPSHOT.jar","className":"edu.baylor.ecs.cms.service.EmsService","methodName":"getINITExams","returnType":"java.util.List<edu.baylor.ecs.cms.model.Exam>","path":"/","httpMethod":"GET","pathParams":null,"queryParams":null,"consumeType":null,"produceType":null,"client":true},{"url":"http://localhost:10002/exam/{1}","applicationName":null,"ribbonServerName":null,"resourcePath":"/Users/abakhtin22/Documents/StaticTools/SARbenchmarks/tms-testbed/tms-cms/target/cms-0.0.1-SNAPSHOT.jar","className":"edu.baylor.ecs.cms.service.EmsService","methodName":"deleteINITExam","returnType":"java.lang.String","path":"/","httpMethod":"DELETE","pathParams":null,"queryParams":null,"consumeType":null,"produceType":null,"client":true},{"url":"http://localhost:10002/exam","applicationName":null,"ribbonServerName":null,"resourcePath":"/Users/abakhtin22/Documents/StaticTools/SARbenchmarks/tms-testbed/tms-cms/target/cms-0.0.1-SNAPSHOT.jar","className":"edu.baylor.ecs.cms.service.EmsService","methodName":"getExams","returnType":"java.util.List<edu.baylor.ecs.cms.model.Exam>","path":"/","httpMethod":"GET","pathParams":null,"queryParams":null,"consumeType":null,"produceType":null,"client":true},{"url":"http://localhost:10002/exam/{1}/questions","applicationName":null,"ribbonServerName":null,"resourcePath":"/Users/abakhtin22/Documents/StaticTools/SARbenchmarks/tms-testbed/tms-cms/target/cms-0.0.1-SNAPSHOT.jar","className":"edu.baylor.ecs.cms.service.EmsService","methodName":"getQuestionsForExam","returnType":"java.util.List<edu.baylor.ecs.cms.model.Question>","path":"/","httpMethod":"GET","pathParams":null,"queryParams":null,"consumeType":null,"produceType":null,"client":true},{"url":"http://localhost:10003/configuration","applicationName":null,"ribbonServerName":null,"resourcePath":"/Users/abakhtin22/Documents/StaticTools/SARbenchmarks/tms-testbed/tms-cms/target/cms-0.0.1-SNAPSHOT.jar","className":"edu.baylor.ecs.cms.controller.ConfigurationController","methodName":"createConfiguration","returnType":"java.lang.Object","path":"/configuration","httpMethod":"POST","pathParams":null,"queryParams":null,"consumeType":null,"produceType":null,"client":false},{"url":"http://localhost:10003/configuration","applicationName":null,"ribbonServerName":null,"resourcePath":"/Users/abakhtin22/Documents/StaticTools/SARbenchmarks/tms-testbed/tms-cms/target/cms-0.0.1-SNAPSHOT.jar","className":"edu.baylor.ecs.cms.controller.ConfigurationController","methodName":"getConfigurations","returnType":"java.lang.Object[]","path":"/configuration","httpMethod":"GET","pathParams":null,"queryParams":null,"consumeType":null,"produceType":null,"client":false},{"url":"http://localhost:9004/userinfo/emailInUse/{1}","applicationName":null,"ribbonServerName":null,"resourcePath":"/Users/abakhtin22/Documents/StaticTools/SARbenchmarks/tms-testbed/tms-cms/target/cms-0.0.1-SNAPSHOT.jar","className":"edu.baylor.ecs.cms.service.UmsService","methodName":"isEmailValid","returnType":"edu.baylor.ecs.cms.dto.EmailDto","path":"/","httpMethod":"GET","pathParams":null,"queryParams":null,"consumeType":null,"produceType":null,"client":true},{"url":"http://localhost:9004/userinfo/userIdByUsername/{1}","applicationName":null,"ribbonServerName":null,"resourcePath":"/Users/abakhtin22/Documents/StaticTools/SARbenchmarks/tms-testbed/tms-cms/target/cms-0.0.1-SNAPSHOT.jar","className":"edu.baylor.ecs.cms.service.UmsService","methodName":"getExamineeId","returnType":"java.lang.String","path":"/","httpMethod":"GET","pathParams":null,"queryParams":null,"consumeType":null,"produceType":null,"client":true},{"url":"http://localhost:9004/userinfo/userById/{1}","applicationName":null,"ribbonServerName":null,"resourcePath":"/Users/abakhtin22/Documents/StaticTools/SARbenchmarks/tms-testbed/tms-cms/target/cms-0.0.1-SNAPSHOT.jar","className":"edu.baylor.ecs.cms.service.UmsService","methodName":"getExamineeInfo","returnType":"edu.baylor.ecs.cms.model.User","path":"/","httpMethod":"GET","pathParams":null,"queryParams":null,"consumeType":null,"produceType":null,"client":true},{"url":"http://localhost:9004/userinfo/users","applicationName":null,"ribbonServerName":null,"resourcePath":"/Users/abakhtin22/Documents/StaticTools/SARbenchmarks/tms-testbed/tms-cms/target/cms-0.0.1-SNAPSHOT.jar","className":"edu.baylor.ecs.cms.service.UmsService","methodName":"getAllUsers","returnType":"java.util.List<java.lang.Object>","path":"/","httpMethod":"GET","pathParams":null,"queryParams":null,"consumeType":null,"produceType":null,"client":true},{"url":"http://localhost:10003/exam/create","applicationName":null,"ribbonServerName":null,"resourcePath":"/Users/abakhtin22/Documents/StaticTools/SARbenchmarks/tms-testbed/tms-cms/target/cms-0.0.1-SNAPSHOT.jar","className":"edu.baylor.ecs.cms.controller.ExamController","methodName":"createExam","returnType":"java.lang.Object","path":"/exam/create","httpMethod":"POST","pathParams":null,"queryParams":null,"consumeType":null,"produceType":null,"client":false},{"url":"http://localhost:10003/exam/{email}","applicationName":null,"ribbonServerName":null,"resourcePath":"/Users/abakhtin22/Documents/StaticTools/SARbenchmarks/tms-testbed/tms-cms/target/cms-0.0.1-SNAPSHOT.jar","className":"edu.baylor.ecs.cms.controller.ExamController","methodName":"isEmailValid","returnType":"edu.baylor.ecs.cms.dto.EmailDto","path":"/exam/{email}","httpMethod":"GET","pathParams":[{"name":"VARIABLE_NAME","defaultValue":""}],"queryParams":null,"consumeType":null,"produceType":null,"client":false},{"url":"http://localhost:10003/exam/{id}/detail","applicationName":null,"ribbonServerName":null,"resourcePath":"/Users/abakhtin22/Documents/StaticTools/SARbenchmarks/tms-testbed/tms-cms/target/cms-0.0.1-SNAPSHOT.jar","className":"edu.baylor.ecs.cms.controller.ExamController","methodName":"getExamDetail","returnType":"java.util.List<edu.baylor.ecs.cms.model.Question>","path":"/exam/{id}/detail","httpMethod":"GET","pathParams":[{"name":"VARIABLE_NAME","defaultValue":""}],"queryParams":null,"consumeType":null,"produceType":"application/json","client":false},{"url":"http://localhost:10003/exam/getAllExamsInStatusINIT","applicationName":null,"ribbonServerName":null,"resourcePath":"/Users/abakhtin22/Documents/StaticTools/SARbenchmarks/tms-testbed/tms-cms/target/cms-0.0.1-SNAPSHOT.jar","className":"edu.baylor.ecs.cms.controller.ExamController","methodName":"getAllExamsInStatusINIT","returnType":"java.util.List<edu.baylor.ecs.cms.model.Exam>","path":"/exam/getAllExamsInStatusINIT","httpMethod":"GET","pathParams":null,"queryParams":null,"consumeType":null,"produceType":"application/json; charset=UTF-8","client":false},{"url":"http://localhost:10003/exam/examineeById/{id}","applicationName":null,"ribbonServerName":null,"resourcePath":"/Users/abakhtin22/Documents/StaticTools/SARbenchmarks/tms-testbed/tms-cms/target/cms-0.0.1-SNAPSHOT.jar","className":"edu.baylor.ecs.cms.controller.ExamController","methodName":"getExamineeById","returnType":"edu.baylor.ecs.cms.model.User","path":"/exam/examineeById/{id}","httpMethod":"GET","pathParams":[{"name":"VARIABLE_NAME","defaultValue":""}],"queryParams":null,"consumeType":null,"produceType":"application/json","client":false},{"url":"http://localhost:10003/exam/deleteExam/{id}","applicationName":null,"ribbonServerName":null,"resourcePath":"/Users/abakhtin22/Documents/StaticTools/SARbenchmarks/tms-testbed/tms-cms/target/cms-0.0.1-SNAPSHOT.jar","className":"edu.baylor.ecs.cms.controller.ExamController","methodName":"deleteExam","returnType":"java.lang.String","path":"/exam/deleteExam/{id}","httpMethod":"DELETE","pathParams":[{"name":"VARIABLE_NAME","defaultValue":""}],"queryParams":null,"consumeType":null,"produceType":null,"client":false},{"url":"http://localhost:10003/exam/users","applicationName":null,"ribbonServerName":null,"resourcePath":"/Users/abakhtin22/Documents/StaticTools/SARbenchmarks/tms-testbed/tms-cms/target/cms-0.0.1-SNAPSHOT.jar","className":"edu.baylor.ecs.cms.controller.ExamController","methodName":"getAllUsers","returnType":"java.util.List<java.lang.Object>","path":"/exam/users","httpMethod":"GET","pathParams":null,"queryParams":null,"consumeType":null,"produceType":null,"client":false},{"url":"http://localhost:10003/exam","applicationName":null,"ribbonServerName":null,"resourcePath":"/Users/abakhtin22/Documents/StaticTools/SARbenchmarks/tms-testbed/tms-cms/target/cms-0.0.1-SNAPSHOT.jar","className":"edu.baylor.ecs.cms.controller.ExamController","methodName":"getAllExams","returnType":"java.util.List<edu.baylor.ecs.cms.model.Exam>","path":"/exam","httpMethod":"GET","pathParams":null,"queryParams":null,"consumeType":null,"produceType":null,"client":false},{"url":"http://localhost:12345/configuration","applicationName":null,"ribbonServerName":null,"resourcePath":"/Users/abakhtin22/Documents/StaticTools/SARbenchmarks/tms-testbed/tms-cms/target/cms-0.0.1-SNAPSHOT.jar","className":"edu.baylor.ecs.cms.service.QmsService","methodName":"createConfiguration","returnType":null,"path":"/","httpMethod":"POST","pathParams":null,"queryParams":null,"consumeType":null,"produceType":null,"client":true},{"url":"http://localhost:12345/categoryinfo","applicationName":null,"ribbonServerName":null,"resourcePath":"/Users/abakhtin22/Documents/StaticTools/SARbenchmarks/tms-testbed/tms-cms/target/cms-0.0.1-SNAPSHOT.jar","className":"edu.baylor.ecs.cms.service.QmsService","methodName":"getCategoryInfoDtos","returnType":"java.util.List<java.lang.Object>","path":"/","httpMethod":"GET","pathParams":null,"queryParams":null,"consumeType":null,"produceType":null,"client":true},{"url":"http://localhost:12345/configuration","applicationName":null,"ribbonServerName":null,"resourcePath":"/Users/abakhtin22/Documents/StaticTools/SARbenchmarks/tms-testbed/tms-cms/target/cms-0.0.1-SNAPSHOT.jar","className":"edu.baylor.ecs.cms.service.QmsService","methodName":"getConfigurations","returnType":null,"path":"/","httpMethod":"GET","pathParams":null,"queryParams":null,"consumeType":null,"produceType":null,"client":true},{"url":"http://localhost:10003/categoryInfo","applicationName":null,"ribbonServerName":null,"resourcePath":"/Users/abakhtin22/Documents/StaticTools/SARbenchmarks/tms-testbed/tms-cms/target/cms-0.0.1-SNAPSHOT.jar","className":"edu.baylor.ecs.cms.controller.CategoryInfoController","methodName":"getCategoryInfo","returnType":"java.util.List<java.lang.Object>","path":"/categoryInfo","httpMethod":"GET","pathParams":null,"queryParams":null,"consumeType":null,"produceType":null,"client":false}]},{"resourcePath":"/Users/abakhtin22/Documents/StaticTools/SARbenchmarks/tms-testbed/tms-ems/target/ems-0.1.0.jar","restEntities":[{"url":"http://localhost:10002/exam/submit/{id}","applicationName":null,"ribbonServerName":null,"resourcePath":"/Users/abakhtin22/Documents/StaticTools/SARbenchmarks/tms-testbed/tms-ems/target/ems-0.1.0.jar","className":"edu.baylor.ecs.ems.controller.ExamController","methodName":"submitExam","returnType":"edu.baylor.ecs.ems.model.Exam","path":"/exam/submit/{id}","httpMethod":"GET","pathParams":[{"name":"id","defaultValue":""}],"queryParams":null,"consumeType":null,"produceType":"application/json","client":false},{"url":"http://localhost:10002/exam/finish/{id}","applicationName":null,"ribbonServerName":null,"resourcePath":"/Users/abakhtin22/Documents/StaticTools/SARbenchmarks/tms-testbed/tms-ems/target/ems-0.1.0.jar","className":"edu.baylor.ecs.ems.controller.ExamController","methodName":"finishExam","returnType":"java.lang.String","path":"/exam/finish/{id}","httpMethod":"GET","pathParams":[{"name":"id","defaultValue":""}],"queryParams":null,"consumeType":null,"produceType":"application/json","client":false},{"url":"http://localhost:10002/exam/{id}","applicationName":null,"ribbonServerName":null,"resourcePath":"/Users/abakhtin22/Documents/StaticTools/SARbenchmarks/tms-testbed/tms-ems/target/ems-0.1.0.jar","className":"edu.baylor.ecs.ems.controller.ExamController","methodName":"deleteINITExam","returnType":"java.lang.String","path":"/exam/{id}","httpMethod":"DELETE","pathParams":[{"name":"VARIABLE_NAME","defaultValue":""}],"queryParams":null,"consumeType":null,"produceType":"application/json","client":false},{"url":"http://localhost:10002/exam","applicationName":null,"ribbonServerName":null,"resourcePath":"/Users/abakhtin22/Documents/StaticTools/SARbenchmarks/tms-testbed/tms-ems/target/ems-0.1.0.jar","className":"edu.baylor.ecs.ems.controller.ExamController","methodName":"listAllExams","returnType":"java.util.List<edu.baylor.ecs.ems.model.Exam>","path":"/exam","httpMethod":"GET","pathParams":null,"queryParams":null,"consumeType":null,"produceType":null,"client":false},{"url":"http://localhost:10002/exam/{id}/questions","applicationName":null,"ribbonServerName":null,"resourcePath":"/Users/abakhtin22/Documents/StaticTools/SARbenchmarks/tms-testbed/tms-ems/target/ems-0.1.0.jar","className":"edu.baylor.ecs.ems.controller.ExamController","methodName":"listAllQuestionsForExam","returnType":"java.util.List<edu.baylor.ecs.ems.model.Question>","path":"/exam/{id}/questions","httpMethod":"GET","pathParams":[{"name":"VARIABLE_NAME","defaultValue":""}],"queryParams":null,"consumeType":null,"produceType":null,"client":false},{"url":"http://localhost:10002/exam","applicationName":null,"ribbonServerName":null,"resourcePath":"/Users/abakhtin22/Documents/StaticTools/SARbenchmarks/tms-testbed/tms-ems/target/ems-0.1.0.jar","className":"edu.baylor.ecs.ems.controller.ExamController","methodName":"createExam","returnType":"edu.baylor.ecs.ems.model.Exam","path":"/exam","httpMethod":"POST","pathParams":null,"queryParams":null,"consumeType":null,"produceType":"application/json; charset=UTF-8","client":false},{"url":"http://localhost:10002/exam/getByUsername/{username}","applicationName":null,"ribbonServerName":null,"resourcePath":"/Users/abakhtin22/Documents/StaticTools/SARbenchmarks/tms-testbed/tms-ems/target/ems-0.1.0.jar","className":"edu.baylor.ecs.ems.controller.ExamController","methodName":"getByUserName","returnType":"java.util.List<edu.baylor.ecs.ems.model.Exam>","path":"/exam/getByUsername/{username}","httpMethod":"GET","pathParams":[{"name":"VARIABLE_NAME","defaultValue":""}],"queryParams":null,"consumeType":null,"produceType":null,"client":false},{"url":"http://localhost:10002/exam/take/{id}","applicationName":null,"ribbonServerName":null,"resourcePath":"/Users/abakhtin22/Documents/StaticTools/SARbenchmarks/tms-testbed/tms-ems/target/ems-0.1.0.jar","className":"edu.baylor.ecs.ems.controller.ExamController","methodName":"takeExam","returnType":"java.util.List<edu.baylor.ecs.ems.dto.QuestionEmsDto>","path":"/exam/take/{id}","httpMethod":"GET","pathParams":[{"name":"id","defaultValue":""}],"queryParams":null,"consumeType":null,"produceType":"application/json","client":false},{"url":"http://localhost:10002/exam/get/{id}","applicationName":null,"ribbonServerName":null,"resourcePath":"/Users/abakhtin22/Documents/StaticTools/SARbenchmarks/tms-testbed/tms-ems/target/ems-0.1.0.jar","className":"edu.baylor.ecs.ems.controller.ExamController","methodName":"getExam","returnType":"edu.baylor.ecs.ems.model.Exam","path":"/exam/get/{id}","httpMethod":"GET","pathParams":[{"name":"id","defaultValue":""}],"queryParams":null,"consumeType":null,"produceType":"application/json","client":false},{"url":"http://localhost:10002/choice","applicationName":null,"ribbonServerName":null,"resourcePath":"/Users/abakhtin22/Documents/StaticTools/SARbenchmarks/tms-testbed/tms-ems/target/ems-0.1.0.jar","className":"edu.baylor.ecs.ems.controller.ChoiceController","methodName":"updateChoices","returnType":"java.util.List<edu.baylor.ecs.ems.model.Choice>","path":"/choice","httpMethod":"POST","pathParams":null,"queryParams":null,"consumeType":null,"produceType":"application/json; charset=UTF-8","client":false},{"url":"http://ums-backend.myicpc.live/userinfo/getId/{1}","applicationName":null,"ribbonServerName":null,"resourcePath":"/Users/abakhtin22/Documents/StaticTools/SARbenchmarks/tms-testbed/tms-ems/target/ems-0.1.0.jar","className":"edu.baylor.ecs.ems.service.UmsService","methodName":"getExamineeId","returnType":"java.lang.String","path":"/","httpMethod":"GET","pathParams":null,"queryParams":null,"consumeType":null,"produceType":null,"client":true},{"url":"http://129.62.148.179:12345/test?configId={1}","applicationName":null,"ribbonServerName":null,"resourcePath":"/Users/abakhtin22/Documents/StaticTools/SARbenchmarks/tms-testbed/tms-ems/target/ems-0.1.0.jar","className":"edu.baylor.ecs.ems.service.QmsService","methodName":"getQuestions","returnType":"java.util.List<edu.baylor.ecs.ems.dto.QuestionQmsDto>","path":"/","httpMethod":"GET","pathParams":null,"queryParams":null,"consumeType":null,"produceType":null,"client":true}]},{"resourcePath":"/Users/abakhtin22/Documents/StaticTools/SARbenchmarks/tms-testbed/tms-qms/target/qms-0.0.1-SNAPSHOT.jar","restEntities":[{"url":"http://localhost:12345/language/{languageId}","applicationName":null,"ribbonServerName":null,"resourcePath":"/Users/abakhtin22/Documents/StaticTools/SARbenchmarks/tms-testbed/tms-qms/target/qms-0.0.1-SNAPSHOT.jar","className":"edu.baylor.ecs.qms.controller.LanguageController","methodName":"findLanguageById","returnType":"edu.baylor.ecs.qms.model.Language","path":"/language/{languageId}","httpMethod":"GET","pathParams":[{"name":"VARIABLE_NAME","defaultValue":""}],"queryParams":null,"consumeType":null,"produceType":null,"client":false},{"url":"http://localhost:12345/language","applicationName":null,"ribbonServerName":null,"resourcePath":"/Users/abakhtin22/Documents/StaticTools/SARbenchmarks/tms-testbed/tms-qms/target/qms-0.0.1-SNAPSHOT.jar","className":"edu.baylor.ecs.qms.controller.LanguageController","methodName":"createLanguage","returnType":"edu.baylor.ecs.qms.model.Language","path":"/language","httpMethod":"POST","pathParams":null,"queryParams":null,"consumeType":null,"produceType":null,"client":false},{"url":"http://localhost:12345/language/{languageId}","applicationName":null,"ribbonServerName":null,"resourcePath":"/Users/abakhtin22/Documents/StaticTools/SARbenchmarks/tms-testbed/tms-qms/target/qms-0.0.1-SNAPSHOT.jar","className":"edu.baylor.ecs.qms.controller.LanguageController","methodName":"deleteLanguage","returnType":null,"path":"/language/{languageId}","httpMethod":"DELETE","pathParams":[{"name":"VARIABLE_NAME","defaultValue":""}],"queryParams":null,"consumeType":null,"produceType":null,"client":false},{"url":"http://localhost:12345/language/{languageId}","applicationName":null,"ribbonServerName":null,"resourcePath":"/Users/abakhtin22/Documents/StaticTools/SARbenchmarks/tms-testbed/tms-qms/target/qms-0.0.1-SNAPSHOT.jar","className":"edu.baylor.ecs.qms.controller.LanguageController","methodName":"updateLanguage","returnType":"edu.baylor.ecs.qms.model.Language","path":"/language/{languageId}","httpMethod":"PUT","pathParams":[{"name":"VARIABLE_NAME","defaultValue":""}],"queryParams":null,"consumeType":null,"produceType":null,"client":false},{"url":"http://localhost:12345/language","applicationName":null,"ribbonServerName":null,"resourcePath":"/Users/abakhtin22/Documents/StaticTools/SARbenchmarks/tms-testbed/tms-qms/target/qms-0.0.1-SNAPSHOT.jar","className":"edu.baylor.ecs.qms.controller.LanguageController","methodName":"findAllLanguages","returnType":"java.util.List<edu.baylor.ecs.qms.model.Language>","path":"/language","httpMethod":"GET","pathParams":null,"queryParams":null,"consumeType":null,"produceType":null,"client":false},{"url":"http://localhost:12345/configuration","applicationName":null,"ribbonServerName":null,"resourcePath":"/Users/abakhtin22/Documents/StaticTools/SARbenchmarks/tms-testbed/tms-qms/target/qms-0.0.1-SNAPSHOT.jar","className":"edu.baylor.ecs.qms.controller.ConfigurationController","methodName":"findAllConfigurations","returnType":"java.util.List<edu.baylor.ecs.qms.model.Configuration>","path":"/configuration","httpMethod":"GET","pathParams":null,"queryParams":null,"consumeType":null,"produceType":null,"client":false},{"url":"http://localhost:12345/configuration","applicationName":null,"ribbonServerName":null,"resourcePath":"/Users/abakhtin22/Documents/StaticTools/SARbenchmarks/tms-testbed/tms-qms/target/qms-0.0.1-SNAPSHOT.jar","className":"edu.baylor.ecs.qms.controller.ConfigurationController","methodName":"createConfiguration","returnType":"edu.baylor.ecs.qms.model.Configuration","path":"/configuration","httpMethod":"POST","pathParams":null,"queryParams":null,"consumeType":null,"produceType":null,"client":false},{"url":"http://localhost:12345/configuration/{configurationId}","applicationName":null,"ribbonServerName":null,"resourcePath":"/Users/abakhtin22/Documents/StaticTools/SARbenchmarks/tms-testbed/tms-qms/target/qms-0.0.1-SNAPSHOT.jar","className":"edu.baylor.ecs.qms.controller.ConfigurationController","methodName":"findConfigurationsById","returnType":"edu.baylor.ecs.qms.model.Configuration","path":"/configuration/{configurationId}","httpMethod":"GET","pathParams":[{"name":"VARIABLE_NAME","defaultValue":""}],"queryParams":null,"consumeType":null,"produceType":null,"client":false},{"url":"http://localhost:12345/configuration/{configurationId}","applicationName":null,"ribbonServerName":null,"resourcePath":"/Users/abakhtin22/Documents/StaticTools/SARbenchmarks/tms-testbed/tms-qms/target/qms-0.0.1-SNAPSHOT.jar","className":"edu.baylor.ecs.qms.controller.ConfigurationController","methodName":"deleteConfiguration","returnType":null,"path":"/configuration/{configurationId}","httpMethod":"DELETE","pathParams":[{"name":"VARIABLE_NAME","defaultValue":""}],"queryParams":null,"consumeType":null,"produceType":null,"client":false},{"url":"http://localhost:12345/test","applicationName":null,"ribbonServerName":null,"resourcePath":"/Users/abakhtin22/Documents/StaticTools/SARbenchmarks/tms-testbed/tms-qms/target/qms-0.0.1-SNAPSHOT.jar","className":"edu.baylor.ecs.qms.controller.TestController","methodName":"createTest","returnType":"java.util.List<edu.baylor.ecs.qms.model.dto.QuestionSingleCodeDto>","path":"/test","httpMethod":"GET","pathParams":null,"queryParams":[{"name":"configId","defaultValue":""}],"consumeType":null,"produceType":null,"client":false},{"url":"http://localhost:12345/categoryinfo","applicationName":null,"ribbonServerName":null,"resourcePath":"/Users/abakhtin22/Documents/StaticTools/SARbenchmarks/tms-testbed/tms-qms/target/qms-0.0.1-SNAPSHOT.jar","className":"edu.baylor.ecs.qms.controller.CategoryInfoController","methodName":"findAllCategoryInfos","returnType":"java.util.List<edu.baylor.ecs.qms.model.dto.CategoryInfoDto>","path":"/categoryinfo","httpMethod":"GET","pathParams":null,"queryParams":null,"consumeType":null,"produceType":null,"client":false},{"url":"http://localhost:12345/category/{categoryId}","applicationName":null,"ribbonServerName":null,"resourcePath":"/Users/abakhtin22/Documents/StaticTools/SARbenchmarks/tms-testbed/tms-qms/target/qms-0.0.1-SNAPSHOT.jar","className":"edu.baylor.ecs.qms.controller.CategoryController","methodName":"updateCategory","returnType":"edu.baylor.ecs.qms.model.Category","path":"/category/{categoryId}","httpMethod":"PUT","pathParams":[{"name":"VARIABLE_NAME","defaultValue":""}],"queryParams":null,"consumeType":null,"produceType":null,"client":false},{"url":"http://localhost:12345/category/{cateogryId}","applicationName":null,"ribbonServerName":null,"resourcePath":"/Users/abakhtin22/Documents/StaticTools/SARbenchmarks/tms-testbed/tms-qms/target/qms-0.0.1-SNAPSHOT.jar","className":"edu.baylor.ecs.qms.controller.CategoryController","methodName":"deleteCategory","returnType":null,"path":"/category/{cateogryId}","httpMethod":"DELETE","pathParams":[{"name":"VARIABLE_NAME","defaultValue":""}],"queryParams":null,"consumeType":null,"produceType":null,"client":false},{"url":"http://localhost:12345/category/{cateogryId}","applicationName":null,"ribbonServerName":null,"resourcePath":"/Users/abakhtin22/Documents/StaticTools/SARbenchmarks/tms-testbed/tms-qms/target/qms-0.0.1-SNAPSHOT.jar","className":"edu.baylor.ecs.qms.controller.CategoryController","methodName":"findCategoriesById","returnType":"edu.baylor.ecs.qms.model.Category","path":"/category/{cateogryId}","httpMethod":"GET","pathParams":[{"name":"VARIABLE_NAME","defaultValue":""}],"queryParams":null,"consumeType":null,"produceType":null,"client":false},{"url":"http://localhost:12345/category","applicationName":null,"ribbonServerName":null,"resourcePath":"/Users/abakhtin22/Documents/StaticTools/SARbenchmarks/tms-testbed/tms-qms/target/qms-0.0.1-SNAPSHOT.jar","className":"edu.baylor.ecs.qms.controller.CategoryController","methodName":"createCategory","returnType":"edu.baylor.ecs.qms.model.Category","path":"/category","httpMethod":"POST","pathParams":null,"queryParams":null,"consumeType":null,"produceType":null,"client":false},{"url":"http://localhost:12345/category","applicationName":null,"ribbonServerName":null,"resourcePath":"/Users/abakhtin22/Documents/StaticTools/SARbenchmarks/tms-testbed/tms-qms/target/qms-0.0.1-SNAPSHOT.jar","className":"edu.baylor.ecs.qms.controller.CategoryController","methodName":"findAllCategories","returnType":"java.util.List<edu.baylor.ecs.qms.model.Category>","path":"/category","httpMethod":"GET","pathParams":null,"queryParams":null,"consumeType":null,"produceType":null,"client":false},{"url":"http://localhost:12345/category/{categoryId}","applicationName":null,"ribbonServerName":null,"resourcePath":"/Users/abakhtin22/Documents/StaticTools/SARbenchmarks/tms-testbed/tms-qms/target/qms-0.0.1-SNAPSHOT.jar","className":"edu.baylor.ecs.qms.controller.CategoryController","methodName":"updateCategoryName","returnType":"edu.baylor.ecs.qms.model.Category","path":"/category/{categoryId}","httpMethod":"PUT","pathParams":[{"name":"VARIABLE_NAME","defaultValue":""}],"queryParams":null,"consumeType":null,"produceType":null,"client":false},{"url":"http://localhost:12345/question","applicationName":null,"ribbonServerName":null,"resourcePath":"/Users/abakhtin22/Documents/StaticTools/SARbenchmarks/tms-testbed/tms-qms/target/qms-0.0.1-SNAPSHOT.jar","className":"edu.baylor.ecs.qms.controller.QuestionController","methodName":"findQuestionByCateogryIdAndName","returnType":"java.util.List<edu.baylor.ecs.qms.model.dto.QuestionDto>","path":"/question","httpMethod":"GET","pathParams":null,"queryParams":[{"name":"VARIABLE_NAME","defaultValue":""}],"consumeType":null,"produceType":null,"client":false},{"url":"http://localhost:12345/question/{questionId}","applicationName":null,"ribbonServerName":null,"resourcePath":"/Users/abakhtin22/Documents/StaticTools/SARbenchmarks/tms-testbed/tms-qms/target/qms-0.0.1-SNAPSHOT.jar","className":"edu.baylor.ecs.qms.controller.QuestionController","methodName":"findQuestionById","returnType":"edu.baylor.ecs.qms.model.Question","path":"/question/{questionId}","httpMethod":"GET","pathParams":[{"name":"VARIABLE_NAME","defaultValue":""}],"queryParams":null,"consumeType":null,"produceType":null,"client":false},{"url":"http://localhost:12345/question/{questionId}","applicationName":null,"ribbonServerName":null,"resourcePath":"/Users/abakhtin22/Documents/StaticTools/SARbenchmarks/tms-testbed/tms-qms/target/qms-0.0.1-SNAPSHOT.jar","className":"edu.baylor.ecs.qms.controller.QuestionController","methodName":"deleteQuestion","returnType":null,"path":"/question/{questionId}","httpMethod":"DELETE","pathParams":[{"name":"VARIABLE_NAME","defaultValue":""}],"queryParams":null,"consumeType":null,"produceType":null,"client":false},{"url":"http://localhost:12345/question/{questionId}","applicationName":null,"ribbonServerName":null,"resourcePath":"/Users/abakhtin22/Documents/StaticTools/SARbenchmarks/tms-testbed/tms-qms/target/qms-0.0.1-SNAPSHOT.jar","className":"edu.baylor.ecs.qms.controller.QuestionController","methodName":"updateQuestion","returnType":"edu.baylor.ecs.qms.model.Question","path":"/question/{questionId}","httpMethod":"PUT","pathParams":[{"name":"VARIABLE_NAME","defaultValue":""}],"queryParams":null,"consumeType":null,"produceType":null,"client":false},{"url":"http://localhost:12345/question/all","applicationName":null,"ribbonServerName":null,"resourcePath":"/Users/abakhtin22/Documents/StaticTools/SARbenchmarks/tms-testbed/tms-qms/target/qms-0.0.1-SNAPSHOT.jar","className":"edu.baylor.ecs.qms.controller.QuestionController","methodName":"findAllQuestions","returnType":"java.util.List<edu.baylor.ecs.qms.model.Question>","path":"/question/all","httpMethod":"GET","pathParams":null,"queryParams":null,"consumeType":null,"produceType":null,"client":false},{"url":"http://localhost:12345/question","applicationName":null,"ribbonServerName":null,"resourcePath":"/Users/abakhtin22/Documents/StaticTools/SARbenchmarks/tms-testbed/tms-qms/target/qms-0.0.1-SNAPSHOT.jar","className":"edu.baylor.ecs.qms.controller.QuestionController","methodName":"createQuestion","returnType":"edu.baylor.ecs.qms.model.Question","path":"/question","httpMethod":"POST","pathParams":null,"queryParams":null,"consumeType":null,"produceType":null,"client":false}]},{"resourcePath":"/Users/abakhtin22/Documents/StaticTools/SARbenchmarks/tms-testbed/tms-ums/target/ums-1.0-SNAPSHOT.jar","restEntities":[{"url":"http://localhost:9004/userinfo/updateUser","applicationName":null,"ribbonServerName":null,"resourcePath":"/Users/abakhtin22/Documents/StaticTools/SARbenchmarks/tms-testbed/tms-ums/target/ums-1.0-SNAPSHOT.jar","className":"edu.baylor.ecs.ums.controller.UserInfoController","methodName":"updateUser","returnType":null,"path":"/userinfo/updateUser","httpMethod":"PUT","pathParams":null,"queryParams":null,"consumeType":null,"produceType":null,"client":false},{"url":"http://localhost:9004/userinfo/deleteUser/{id}","applicationName":null,"ribbonServerName":null,"resourcePath":"/Users/abakhtin22/Documents/StaticTools/SARbenchmarks/tms-testbed/tms-ums/target/ums-1.0-SNAPSHOT.jar","className":"edu.baylor.ecs.ums.controller.UserInfoController","methodName":"removeUser","returnType":null,"path":"/userinfo/deleteUser/{id}","httpMethod":"DELETE","pathParams":[{"name":"VARIABLE_NAME","defaultValue":""}],"queryParams":null,"consumeType":null,"produceType":null,"client":false},{"url":"http://localhost:9004/userinfo/deleteUserByUsername/{username}","applicationName":null,"ribbonServerName":null,"resourcePath":"/Users/abakhtin22/Documents/StaticTools/SARbenchmarks/tms-testbed/tms-ums/target/ums-1.0-SNAPSHOT.jar","className":"edu.baylor.ecs.ums.controller.UserInfoController","methodName":"removeUserByUsername","returnType":null,"path":"/userinfo/deleteUserByUsername/{username}","httpMethod":"DELETE","pathParams":[{"name":"VARIABLE_NAME","defaultValue":""}],"queryParams":null,"consumeType":null,"produceType":null,"client":false},{"url":"http://localhost:9004/userinfo/addUser","applicationName":null,"ribbonServerName":null,"resourcePath":"/Users/abakhtin22/Documents/StaticTools/SARbenchmarks/tms-testbed/tms-ums/target/ums-1.0-SNAPSHOT.jar","className":"edu.baylor.ecs.ums.controller.UserInfoController","methodName":"addNewUser","returnType":null,"path":"/userinfo/addUser","httpMethod":"POST","pathParams":null,"queryParams":null,"consumeType":null,"produceType":null,"client":false},{"url":"http://localhost:9004/userinfo/emailInUse/{email}","applicationName":null,"ribbonServerName":null,"resourcePath":"/Users/abakhtin22/Documents/StaticTools/SARbenchmarks/tms-testbed/tms-ums/target/ums-1.0-SNAPSHOT.jar","className":"edu.baylor.ecs.ums.controller.UserInfoController","methodName":"isEmailInUse","returnType":null,"path":"/userinfo/emailInUse/{email}","httpMethod":"GET","pathParams":[{"name":"VARIABLE_NAME","defaultValue":""}],"queryParams":null,"consumeType":null,"produceType":null,"client":false},{"url":"http://localhost:9004/userinfo/addUserRoles/{username}","applicationName":null,"ribbonServerName":null,"resourcePath":"/Users/abakhtin22/Documents/StaticTools/SARbenchmarks/tms-testbed/tms-ums/target/ums-1.0-SNAPSHOT.jar","className":"edu.baylor.ecs.ums.controller.UserInfoController","methodName":"addUserRoles","returnType":null,"path":"/userinfo/addUserRoles/{username}","httpMethod":"POST","pathParams":[{"name":"VARIABLE_NAME","defaultValue":""}],"queryParams":null,"consumeType":null,"produceType":null,"client":false},{"url":"http://localhost:9004/userinfo/validId/{id}","applicationName":null,"ribbonServerName":null,"resourcePath":"/Users/abakhtin22/Documents/StaticTools/SARbenchmarks/tms-testbed/tms-ums/target/ums-1.0-SNAPSHOT.jar","className":"edu.baylor.ecs.ums.controller.UserInfoController","methodName":"isValidId","returnType":null,"path":"/userinfo/validId/{id}","httpMethod":"GET","pathParams":[{"name":"VARIABLE_NAME","defaultValue":""}],"queryParams":null,"consumeType":null,"produceType":null,"client":false},{"url":"http://localhost:9004/userinfo/userRoles/{username}","applicationName":null,"ribbonServerName":null,"resourcePath":"/Users/abakhtin22/Documents/StaticTools/SARbenchmarks/tms-testbed/tms-ums/target/ums-1.0-SNAPSHOT.jar","className":"edu.baylor.ecs.ums.controller.UserInfoController","methodName":"getUserRoles","returnType":null,"path":"/userinfo/userRoles/{username}","httpMethod":"GET","pathParams":[{"name":"VARIABLE_NAME","defaultValue":""}],"queryParams":null,"consumeType":null,"produceType":null,"client":false},{"url":"http://localhost:9004/userinfo/users","applicationName":null,"ribbonServerName":null,"resourcePath":"/Users/abakhtin22/Documents/StaticTools/SARbenchmarks/tms-testbed/tms-ums/target/ums-1.0-SNAPSHOT.jar","className":"edu.baylor.ecs.ums.controller.UserInfoController","methodName":"getAllUsers","returnType":null,"path":"/userinfo/users","httpMethod":"GET","pathParams":null,"queryParams":null,"consumeType":null,"produceType":null,"client":false},{"url":"http://localhost:9004/userinfo/userById/{id}","applicationName":null,"ribbonServerName":null,"resourcePath":"/Users/abakhtin22/Documents/StaticTools/SARbenchmarks/tms-testbed/tms-ums/target/ums-1.0-SNAPSHOT.jar","className":"edu.baylor.ecs.ums.controller.UserInfoController","methodName":"getUserById","returnType":null,"path":"/userinfo/userById/{id}","httpMethod":"GET","pathParams":[{"name":"VARIABLE_NAME","defaultValue":""}],"queryParams":null,"consumeType":null,"produceType":null,"client":false},{"url":"http://localhost:9004/userinfo/usernames","applicationName":null,"ribbonServerName":null,"resourcePath":"/Users/abakhtin22/Documents/StaticTools/SARbenchmarks/tms-testbed/tms-ums/target/ums-1.0-SNAPSHOT.jar","className":"edu.baylor.ecs.ums.controller.UserInfoController","methodName":"getAllUsernames","returnType":null,"path":"/userinfo/usernames","httpMethod":"GET","pathParams":null,"queryParams":null,"consumeType":null,"produceType":null,"client":false},{"url":"http://localhost:9004/userinfo/changePassword/{id}","applicationName":null,"ribbonServerName":null,"resourcePath":"/Users/abakhtin22/Documents/StaticTools/SARbenchmarks/tms-testbed/tms-ums/target/ums-1.0-SNAPSHOT.jar","className":"edu.baylor.ecs.ums.controller.UserInfoController","methodName":"changePassword","returnType":null,"path":"/userinfo/changePassword/{id}","httpMethod":"PUT","pathParams":[{"name":"VARIABLE_NAME","defaultValue":""}],"queryParams":null,"consumeType":null,"produceType":null,"client":false},{"url":"http://localhost:9004/userinfo/userByUsername/{username}","applicationName":null,"ribbonServerName":null,"resourcePath":"/Users/abakhtin22/Documents/StaticTools/SARbenchmarks/tms-testbed/tms-ums/target/ums-1.0-SNAPSHOT.jar","className":"edu.baylor.ecs.ums.controller.UserInfoController","methodName":"getUserByUsername","returnType":null,"path":"/userinfo/userByUsername/{username}","httpMethod":"GET","pathParams":[{"name":"VARIABLE_NAME","defaultValue":""}],"queryParams":null,"consumeType":null,"produceType":null,"client":false}]}],"restFlowContext":{"restFlows":[{"resourcePath":"/Users/abakhtin22/Documents/StaticTools/SARbenchmarks/tms-testbed/tms-cms/target/cms-0.0.1-SNAPSHOT.jar","className":"edu.baylor.ecs.cms.service.EmsService","methodName":"createExam","servers":[{"url":"http://localhost:10002/exam","applicationName":null,"ribbonServerName":null,"resourcePath":"/Users/abakhtin22/Documents/StaticTools/SARbenchmarks/tms-testbed/tms-ems/target/ems-0.1.0.jar","className":"edu.baylor.ecs.ems.controller.ExamController","methodName":"createExam","returnType":"edu.baylor.ecs.ems.model.Exam","path":"/exam","httpMethod":"POST","pathParams":null,"queryParams":null,"consumeType":null,"produceType":"application/json; charset=UTF-8","client":false}]},{"resourcePath":"/Users/abakhtin22/Documents/StaticTools/SARbenchmarks/tms-testbed/tms-cms/target/cms-0.0.1-SNAPSHOT.jar","className":"edu.baylor.ecs.cms.service.EmsService","methodName":"getINITExams","servers":[{"url":"http://localhost:10002/exam","applicationName":null,"ribbonServerName":null,"resourcePath":"/Users/abakhtin22/Documents/StaticTools/SARbenchmarks/tms-testbed/tms-ems/target/ems-0.1.0.jar","className":"edu.baylor.ecs.ems.controller.ExamController","methodName":"listAllExams","returnType":"java.util.List<edu.baylor.ecs.ems.model.Exam>","path":"/exam","httpMethod":"GET","pathParams":null,"queryParams":null,"consumeType":null,"produceType":null,"client":false}]},{"resourcePath":"/Users/abakhtin22/Documents/StaticTools/SARbenchmarks/tms-testbed/tms-cms/target/cms-0.0.1-SNAPSHOT.jar","className":"edu.baylor.ecs.cms.service.EmsService","methodName":"deleteINITExam","servers":[{"url":"http://localhost:10002/exam/{id}","applicationName":null,"ribbonServerName":null,"resourcePath":"/Users/abakhtin22/Documents/StaticTools/SARbenchmarks/tms-testbed/tms-ems/target/ems-0.1.0.jar","className":"edu.baylor.ecs.ems.controller.ExamController","methodName":"deleteINITExam","returnType":"java.lang.String","path":"/exam/{id}","httpMethod":"DELETE","pathParams":[{"name":"VARIABLE_NAME","defaultValue":""}],"queryParams":null,"consumeType":null,"produceType":"application/json","client":false}]},{"resourcePath":"/Users/abakhtin22/Documents/StaticTools/SARbenchmarks/tms-testbed/tms-cms/target/cms-0.0.1-SNAPSHOT.jar","className":"edu.baylor.ecs.cms.service.EmsService","methodName":"getExams","servers":[{"url":"http://localhost:10002/exam","applicationName":null,"ribbonServerName":null,"resourcePath":"/Users/abakhtin22/Documents/StaticTools/SARbenchmarks/tms-testbed/tms-ems/target/ems-0.1.0.jar","className":"edu.baylor.ecs.ems.controller.ExamController","methodName":"listAllExams","returnType":"java.util.List<edu.baylor.ecs.ems.model.Exam>","path":"/exam","httpMethod":"GET","pathParams":null,"queryParams":null,"consumeType":null,"produceType":null,"client":false}]},{"resourcePath":"/Users/abakhtin22/Documents/StaticTools/SARbenchmarks/tms-testbed/tms-cms/target/cms-0.0.1-SNAPSHOT.jar","className":"edu.baylor.ecs.cms.service.EmsService","methodName":"getQuestionsForExam","servers":[{"url":"http://localhost:10002/exam/{id}/questions","applicationName":null,"ribbonServerName":null,"resourcePath":"/Users/abakhtin22/Documents/StaticTools/SARbenchmarks/tms-testbed/tms-ems/target/ems-0.1.0.jar","className":"edu.baylor.ecs.ems.controller.ExamController","methodName":"listAllQuestionsForExam","returnType":"java.util.List<edu.baylor.ecs.ems.model.Question>","path":"/exam/{id}/questions","httpMethod":"GET","pathParams":[{"name":"VARIABLE_NAME","defaultValue":""}],"queryParams":null,"consumeType":null,"produceType":null,"client":false}]},{"resourcePath":"/Users/abakhtin22/Documents/StaticTools/SARbenchmarks/tms-testbed/tms-cms/target/cms-0.0.1-SNAPSHOT.jar","className":"edu.baylor.ecs.cms.service.UmsService","methodName":"isEmailValid","servers":[{"url":"http://localhost:9004/userinfo/emailInUse/{email}","applicationName":null,"ribbonServerName":null,"resourcePath":"/Users/abakhtin22/Documents/StaticTools/SARbenchmarks/tms-testbed/tms-ums/target/ums-1.0-SNAPSHOT.jar","className":"edu.baylor.ecs.ums.controller.UserInfoController","methodName":"isEmailInUse","returnType":null,"path":"/userinfo/emailInUse/{email}","httpMethod":"GET","pathParams":[{"name":"VARIABLE_NAME","defaultValue":""}],"queryParams":null,"consumeType":null,"produceType":null,"client":false}]},{"resourcePath":"/Users/abakhtin22/Documents/StaticTools/SARbenchmarks/tms-testbed/tms-cms/target/cms-0.0.1-SNAPSHOT.jar","className":"edu.baylor.ecs.cms.service.UmsService","methodName":"getExamineeInfo","servers":[{"url":"http://localhost:9004/userinfo/userById/{id}","applicationName":null,"ribbonServerName":null,"resourcePath":"/Users/abakhtin22/Documents/StaticTools/SARbenchmarks/tms-testbed/tms-ums/target/ums-1.0-SNAPSHOT.jar","className":"edu.baylor.ecs.ums.controller.UserInfoController","methodName":"getUserById","returnType":null,"path":"/userinfo/userById/{id}","httpMethod":"GET","pathParams":[{"name":"VARIABLE_NAME","defaultValue":""}],"queryParams":null,"consumeType":null,"produceType":null,"client":false}]},{"resourcePath":"/Users/abakhtin22/Documents/StaticTools/SARbenchmarks/tms-testbed/tms-cms/target/cms-0.0.1-SNAPSHOT.jar","className":"edu.baylor.ecs.cms.service.UmsService","methodName":"getAllUsers","servers":[{"url":"http://localhost:9004/userinfo/users","applicationName":null,"ribbonServerName":null,"resourcePath":"/Users/abakhtin22/Documents/StaticTools/SARbenchmarks/tms-testbed/tms-ums/target/ums-1.0-SNAPSHOT.jar","className":"edu.baylor.ecs.ums.controller.UserInfoController","methodName":"getAllUsers","returnType":null,"path":"/userinfo/users","httpMethod":"GET","pathParams":null,"queryParams":null,"consumeType":null,"produceType":null,"client":false}]},{"resourcePath":"/Users/abakhtin22/Documents/StaticTools/SARbenchmarks/tms-testbed/tms-cms/target/cms-0.0.1-SNAPSHOT.jar","className":"edu.baylor.ecs.cms.service.QmsService","methodName":"createConfiguration","servers":[{"url":"http://localhost:12345/configuration","applicationName":null,"ribbonServerName":null,"resourcePath":"/Users/abakhtin22/Documents/StaticTools/SARbenchmarks/tms-testbed/tms-qms/target/qms-0.0.1-SNAPSHOT.jar","className":"edu.baylor.ecs.qms.controller.ConfigurationController","methodName":"createConfiguration","returnType":"edu.baylor.ecs.qms.model.Configuration","path":"/configuration","httpMethod":"POST","pathParams":null,"queryParams":null,"consumeType":null,"produceType":null,"client":false}]},{"resourcePath":"/Users/abakhtin22/Documents/StaticTools/SARbenchmarks/tms-testbed/tms-cms/target/cms-0.0.1-SNAPSHOT.jar","className":"edu.baylor.ecs.cms.service.QmsService","methodName":"getCategoryInfoDtos","servers":[{"url":"http://localhost:12345/categoryinfo","applicationName":null,"ribbonServerName":null,"resourcePath":"/Users/abakhtin22/Documents/StaticTools/SARbenchmarks/tms-testbed/tms-qms/target/qms-0.0.1-SNAPSHOT.jar","className":"edu.baylor.ecs.qms.controller.CategoryInfoController","methodName":"findAllCategoryInfos","returnType":"java.util.List<edu.baylor.ecs.qms.model.dto.CategoryInfoDto>","path":"/categoryinfo","httpMethod":"GET","pathParams":null,"queryParams":null,"consumeType":null,"produceType":null,"client":false}]},{"resourcePath":"/Users/abakhtin22/Documents/StaticTools/SARbenchmarks/tms-testbed/tms-cms/target/cms-0.0.1-SNAPSHOT.jar","className":"edu.baylor.ecs.cms.service.QmsService","methodName":"getConfigurations","servers":[{"url":"http://localhost:12345/configuration","applicationName":null,"ribbonServerName":null,"resourcePath":"/Users/abakhtin22/Documents/StaticTools/SARbenchmarks/tms-testbed/tms-qms/target/qms-0.0.1-SNAPSHOT.jar","className":"edu.baylor.ecs.qms.controller.ConfigurationController","methodName":"findAllConfigurations","returnType":"java.util.List<edu.baylor.ecs.qms.model.Configuration>","path":"/configuration","httpMethod":"GET","pathParams":null,"queryParams":null,"consumeType":null,"produceType":null,"client":false}]}]}}